turingmind_mcp/__init__.py
turingmind_mcp/py.typed
turingmind_mcp/server.py
turingmind_mcp-0.2.0.dist-info/METADATA
turingmind_mcp-0.2.0.dist-info/WHEEL
turingmind_mcp-0.2.0.dist-info/entry_points.txt
turingmind_mcp-0.2.0.dist-info/licenses/LICENSE
turingmind_mcp-0.2.0.dist-info/RECORD
