Metadata-Version: 2.4
Name: turingmind-mcp
Version: 0.2.0
Summary: MCP server for TuringMind cloud - provides type-safe tools for authentication, code reviews, and feedback
Project-URL: Homepage, https://turingmind.ai
Project-URL: Documentation, https://docs.turingmind.ai/mcp
Project-URL: Repository, https://github.com/turingmindai/turingmind-mcp
Project-URL: Issues, https://github.com/turingmindai/turingmind-mcp/issues
Project-URL: Changelog, https://github.com/turingmindai/turingmind-mcp/blob/main/CHANGELOG.md
Author-email: TuringMind <support@turingmind.ai>
Maintainer-email: TuringMind Team <support@turingmind.ai>
License: MIT
License-File: LICENSE
Keywords: ai,anthropic,claude,code-review,mcp,model-context-protocol,security,static-analysis,turingmind
Classifier: Development Status :: 4 - Beta
Classifier: Environment :: Console
Classifier: Intended Audience :: Developers
Classifier: License :: OSI Approved :: MIT License
Classifier: Operating System :: OS Independent
Classifier: Programming Language :: Python :: 3
Classifier: Programming Language :: Python :: 3.10
Classifier: Programming Language :: Python :: 3.11
Classifier: Programming Language :: Python :: 3.12
Classifier: Programming Language :: Python :: 3.13
Classifier: Topic :: Security
Classifier: Topic :: Software Development :: Quality Assurance
Classifier: Topic :: Software Development :: Testing
Classifier: Typing :: Typed
Requires-Python: >=3.10
Requires-Dist: httpx>=0.25.0
Requires-Dist: mcp>=1.0.0
Requires-Dist: pydantic>=2.0.0
Provides-Extra: dev
Requires-Dist: black>=23.0.0; extra == 'dev'
Requires-Dist: mypy>=1.0.0; extra == 'dev'
Requires-Dist: pytest-asyncio>=0.21.0; extra == 'dev'
Requires-Dist: pytest-cov>=4.0.0; extra == 'dev'
Requires-Dist: pytest>=7.0.0; extra == 'dev'
Requires-Dist: ruff>=0.1.0; extra == 'dev'
